<?xml version="1.0" encoding="UTF-8"?>
<objects serializationModel="Studio.02.02.00">
	<object class="AudioFile" id="{1897900f-e20b-410a-afeb-fe4bb71f9d00}">
		<property name="assetPath">
			<value>Cutscene.ogg</value>
		</property>
		<property name="isStreaming">
			<value>true</value>
		</property>
		<property name="frequencyInKHz">
			<value>48</value>
		</property>
		<property name="channelCount">
			<value>2</value>
		</property>
		<property name="length">
			<value>24.233333333333334</value>
		</property>
		<relationship name="masterAssetFolder">
			<destination>{c488a745-ae80-481d-9a75-e9afd2128db3}</destination>
		</relationship>
	</object>
</objects>
